pytgclient/__init__.py
pytgclient/pytgclient.py
pytgclient-1.0.0.dist-info/licenses/LICENSE
pytgclient-1.0.0.dist-info/WHEEL
pytgclient-1.0.0.dist-info/METADATA
pytgclient-1.0.0.dist-info/RECORD
