Metadata-Version: 2.4
Name: pytgclient
Version: 1.0.0
Summary: TLib - مكتبة Python للتفاعل مع Telegram Bot API بسهولة وفعالية
Author-email: Aymen MW <aymenmw@proton.me>
License-Expression: Apache-2.0
License-File: LICENSE
